deutschland/abfallnavi/__init__.py
deutschland/abfallnavi/api/__init__.py
deutschland/abfallnavi/api/abholpunkte_api.py
deutschland/abfallnavi/api/fraktionen_api.py
deutschland/abfallnavi/api/termine_api.py
deutschland/abfallnavi/api_client.py
deutschland/abfallnavi/apis/__init__.py
deutschland/abfallnavi/configuration.py
deutschland/abfallnavi/exceptions.py
deutschland/abfallnavi/model/__init__.py
deutschland/abfallnavi/model/abholung.py
deutschland/abfallnavi/model/bezirk.py
deutschland/abfallnavi/model/fraktion.py
deutschland/abfallnavi/model/hausnummer.py
deutschland/abfallnavi/model/ort.py
deutschland/abfallnavi/model/ort2.py
deutschland/abfallnavi/model/ort_inner.py
deutschland/abfallnavi/model/region.py
deutschland/abfallnavi/model/strasse.py
deutschland/abfallnavi/model_utils.py
deutschland/abfallnavi/models/__init__.py
deutschland/abfallnavi/rest.py
de_abfallnavi-0.1.0.dist-info/WHEEL
de_abfallnavi-0.1.0.dist-info/METADATA
de_abfallnavi-0.1.0.dist-info/RECORD
